MANIFEST.in
setup.py
detektor/__init__.py
detektor/comparer.py
detektor/parser.py
detektor/parseresult.py
detektor.egg-info/PKG-INFO
detektor.egg-info/SOURCES.txt
detektor.egg-info/dependency_links.txt
detektor.egg-info/not-zip-safe
detektor.egg-info/requires.txt
detektor.egg-info/top_level.txt
detektor/codefilter/__init__.py
detektor/codefilter/base.py
detektor/codefilter/normalizeoperatorwhitespace.py
detektor/functionextractor/__init__.py
detektor/functionextractor/base.py
detektor/functionextractor/clike.py
detektor/languageparser/__init__.py
detektor/languageparser/base.py
detektor/languageparser/java.py
detektor/languageparser/python.py
detektor/languageparser/shlexparser.py
detektor/tests/__init__.py
detektor/tests/test_parseresultcomparer.py
detektor/tests/functionextractor/__init__.py
detektor/tests/functionextractor/test_clike.py
detektor/tests/languageparser/__init__.py
detektor/tests/languageparser/test_java.py
detektor/tests/languageparser/test_python.py