Metadata-Version: 1.1
Name: detektor
Version: 1.1.0-beta.001
Summary: A library for finding similarities in code.
Home-page: https://github.com/appressoas/detektor
Author: Magne Westlie, Espen Angell Kristiansen, Tor Ivar Johansen
Author-email: magne@appresso.no,espen@appresso.no,tor@appresso.no
License: GPL
Platform: UNKNOWN
Classifier: Development Status :: 4 - Beta
Classifier: Intended Audience :: Developers
Classifier: License :: OSI Approved
Classifier: Operating System :: OS Independent
Classifier: Programming Language :: Python
